audiotokenizer.py
default_speakers/chinenye.json
default_speakers/emma.json
default_speakers/idera.json
default_speakers/joke.json
default_speakers/jude.json
default_speakers/onye.json
default_speakers/osagie.json
default_speakers/regina.json
default_speakers/remi.json
default_speakers/tayo.json
default_speakers/umar.json
default_speakers_local/hausa_female1.json
default_speakers_local/hausa_female2.json
default_speakers_local/hausa_male1.json
default_speakers_local/hausa_male2.json
default_speakers_local/igbo_female1.json
default_speakers_local/igbo_female2.json
default_speakers_local/igbo_male2.json
default_speakers_local/yoruba_female1.json
default_speakers_local/yoruba_female2.json
default_speakers_local/yoruba_male1.json
default_speakers_local/yoruba_male2.json
yarngpt/__init__.py
yarngpt/core.py
yarngpt-0.2.0.dist-info/LICENSE
yarngpt-0.2.0.dist-info/METADATA
yarngpt-0.2.0.dist-info/WHEEL
yarngpt-0.2.0.dist-info/top_level.txt
yarngpt-0.2.0.dist-info/RECORD
