Metadata-Version: 2.2
Name: yarngpt
Version: 0.2.0
Summary: A Python wrapper for YarnGPT text-to-speech model with multi-language support
Author-email: Abayomi Olagunju <olagunjujeremiah@gmail.com>
Project-URL: Homepage, https://github.com/jerryola1
Classifier: Programming Language :: Python :: 3
Classifier: License :: OSI Approved :: MIT License
Classifier: Natural Language :: English
Classifier: Development Status :: 4 - Beta
Classifier: Intended Audience :: Developers
Classifier: Topic :: Software Development :: Libraries :: Python Modules
Classifier: Topic :: Multimedia :: Sound/Audio :: Speech
Requires-Python: >=3.6
License-File: LICENSE
Requires-Dist: torch
Requires-Dist: transformers
Requires-Dist: torchaudio
Requires-Dist: outetts>=0.3.0
Requires-Dist: uroman
Requires-Dist: numpy
Requires-Dist: inflect
Requires-Dist: IPython
Requires-Dist: tqdm
